{
  "snow": {
    "type": "mindustry.content.Weathers$1",
    "name": "snow",
    "iconId": 0,
    "inlineDescription": true,
    "alwaysUnlocked": false,
    "localizedName": "Snow",
    "statusGround": true,
    "statusAir": true,
    "statusDuration": 120,
    "hidden": false,
    "soundVolOscScl": 1100,
    "soundVolOscMag": 1.5,
    "soundVolMin": 0.019999999552965164,
    "soundVol": 0,
    "opacityMultiplier": 1,
    "duration": 36000,
    "noisePath": "noiseAlpha",
    "noiseLayerColorM": 1,
    "noiseLayerSclM": 0.9900000095367432,
    "noiseLayerAlphaM": 0.800000011920929,
    "noiseLayerSpeedM": 1.100000023841858,
    "noiseLayers": 1,
    "randomParticleRotation": false,
    "useWindVector": false,
    "drawParticles": true,
    "drawNoise": false,
    "sinMagMax": 7,
    "sinMagMin": 1,
    "sinSclMax": 80,
    "sinSclMin": 30,
    "baseSpeed": 6.099999904632568,
    "noiseScale": 2000,
    "force": 0,
    "maxAlpha": 1,
    "minAlpha": 1,
    "density": 1200,
    "sizeMax": 13,
    "sizeMin": 2.5999999046325684,
    "padding": 16,
    "xspeed": 0.25,
    "yspeed": -2,
    "particleRegion": "particle"
  },
  "rain": {
    "type": "mindustry.content.Weathers$2",
    "name": "rain",
    "iconId": 0,
    "inlineDescription": true,
    "alwaysUnlocked": false,
    "localizedName": "Rain",
    "statusGround": true,
    "statusAir": true,
    "statusDuration": 120,
    "hidden": false,
    "soundVolOscScl": 20,
    "soundVolOscMag": 0,
    "soundVolMin": 0,
    "soundVol": 0.25,
    "opacityMultiplier": 1,
    "duration": 36000,
    "splashTimeScale": 22,
    "sizeMax": 40,
    "sizeMin": 8,
    "stroke": 0.75,
    "density": 1200,
    "padding": 16,
    "xspeed": 1.5,
    "yspeed": 5
  },
  "sandstorm": {
    "type": "mindustry.content.Weathers$3",
    "name": "sandstorm",
    "iconId": 0,
    "inlineDescription": true,
    "alwaysUnlocked": false,
    "localizedName": "Sandstorm",
    "statusGround": true,
    "statusAir": true,
    "statusDuration": 120,
    "hidden": false,
    "soundVolOscScl": 20,
    "soundVolOscMag": 0,
    "soundVolMin": 0,
    "soundVol": 0.800000011920929,
    "opacityMultiplier": 0.3499999940395355,
    "duration": 25200,
    "noisePath": "noiseAlpha",
    "noiseLayerColorM": 1,
    "noiseLayerSclM": 0.9900000095367432,
    "noiseLayerAlphaM": 0.800000011920929,
    "noiseLayerSpeedM": 1.100000023841858,
    "noiseLayers": 1,
    "randomParticleRotation": false,
    "useWindVector": true,
    "drawParticles": true,
    "drawNoise": true,
    "sinMagMax": 7,
    "sinMagMin": 1,
    "sinSclMax": 80,
    "sinSclMin": 30,
    "baseSpeed": 5.400000095367432,
    "noiseScale": 2000,
    "force": 0.10000000149011612,
    "maxAlpha": 0.20000000298023224,
    "minAlpha": 0,
    "density": 1500,
    "sizeMax": 140,
    "sizeMin": 70,
    "padding": 16,
    "xspeed": 0.25,
    "yspeed": -2,
    "particleRegion": "particle"
  },
  "sporestorm": {
    "type": "mindustry.content.Weathers$4",
    "name": "sporestorm",
    "iconId": 0,
    "inlineDescription": true,
    "alwaysUnlocked": false,
    "localizedName": "Sporestorm",
    "statusGround": false,
    "statusAir": true,
    "statusDuration": 120,
    "hidden": false,
    "soundVolOscScl": 20,
    "soundVolOscMag": 0,
    "soundVolMin": 0,
    "soundVol": 0.699999988079071,
    "opacityMultiplier": 0.5,
    "duration": 25200,
    "noisePath": "noiseAlpha",
    "noiseLayerColorM": 1,
    "noiseLayerSclM": 0.9900000095367432,
    "noiseLayerAlphaM": 0.800000011920929,
    "noiseLayerSpeedM": 1.100000023841858,
    "noiseLayers": 1,
    "randomParticleRotation": false,
    "useWindVector": true,
    "drawParticles": true,
    "drawNoise": true,
    "sinMagMax": 7,
    "sinMagMin": 1,
    "sinSclMax": 80,
    "sinSclMin": 30,
    "baseSpeed": 4.300000190734863,
    "noiseScale": 2000,
    "force": 0.10000000149011612,
    "maxAlpha": 0.800000011920929,
    "minAlpha": 0.10000000149011612,
    "density": 2000,
    "sizeMax": 5,
    "sizeMin": 2.5,
    "padding": 16,
    "xspeed": 0.25,
    "yspeed": -2,
    "particleRegion": "circle-small"
  },
  "fog": {
    "type": "mindustry.content.Weathers$5",
    "name": "fog",
    "iconId": 0,
    "inlineDescription": true,
    "alwaysUnlocked": false,
    "localizedName": "Fog",
    "statusGround": true,
    "statusAir": true,
    "statusDuration": 120,
    "hidden": false,
    "soundVolOscScl": 20,
    "soundVolOscMag": 0,
    "soundVolMin": 0,
    "soundVol": 0.10000000149011612,
    "opacityMultiplier": 0.4699999988079071,
    "duration": 54000,
    "noisePath": "fog",
    "noiseLayerColorM": 1,
    "noiseLayerSclM": 0.6000000238418579,
    "noiseLayerAlphaM": 0.699999988079071,
    "noiseLayerSpeedM": 2,
    "noiseLayers": 3,
    "randomParticleRotation": false,
    "useWindVector": false,
    "drawParticles": false,
    "drawNoise": true,
    "sinMagMax": 7,
    "sinMagMin": 1,
    "sinSclMax": 80,
    "sinSclMin": 30,
    "baseSpeed": 0.05000000074505806,
    "noiseScale": 1100,
    "force": 0,
    "maxAlpha": 1,
    "minAlpha": 1,
    "density": 1200,
    "sizeMax": 12,
    "sizeMin": 2.4000000953674316,
    "padding": 16,
    "xspeed": 1,
    "yspeed": 0.009999999776482582,
    "particleRegion": "circle-shadow"
  },
  "suspend-particles": {
    "type": "mindustry.content.Weathers$6",
    "name": "suspend-particles",
    "iconId": 0,
    "inlineDescription": true,
    "alwaysUnlocked": false,
    "localizedName": "suspend-particles",
    "statusGround": false,
    "statusAir": true,
    "statusDuration": 120,
    "hidden": true,
    "soundVolOscScl": 20,
    "soundVolOscMag": 0,
    "soundVolMin": 0,
    "soundVol": 0.10000000149011612,
    "opacityMultiplier": 1,
    "duration": 36000,
    "noisePath": "noiseAlpha",
    "noiseLayerColorM": 1,
    "noiseLayerSclM": 0.9900000095367432,
    "noiseLayerAlphaM": 0.800000011920929,
    "noiseLayerSpeedM": 1.100000023841858,
    "noiseLayers": 1,
    "randomParticleRotation": false,
    "useWindVector": true,
    "drawParticles": true,
    "drawNoise": false,
    "sinMagMax": 7,
    "sinMagMin": 1,
    "sinSclMax": 80,
    "sinSclMin": 30,
    "baseSpeed": 0.029999999329447746,
    "noiseScale": 2000,
    "force": 0,
    "maxAlpha": 1,
    "minAlpha": 0.5,
    "density": 10000,
    "sizeMax": 4,
    "sizeMin": 1.399999976158142,
    "padding": 16,
    "xspeed": 0.25,
    "yspeed": -2,
    "particleRegion": "particle"
  }
}
